QuickWall/SetPaper.py
QuickWall/__init__.py
QuickWall/__main__.py
QuickWall/blacklist.py
QuickWall/feh.py
QuickWall/gnome.py
QuickWall/kde.py
QuickWall/nitrogen.py
QuickWall/setter.py
QuickWall/utility.py
QuickWall/wal.py
QuickWall/wall.py
QuickWall/xfce.py
QuickWall-0.0.5.dist-info/LICENSE
QuickWall-0.0.5.dist-info/METADATA
QuickWall-0.0.5.dist-info/WHEEL
QuickWall-0.0.5.dist-info/entry_points.txt
QuickWall-0.0.5.dist-info/top_level.txt
QuickWall-0.0.5.dist-info/RECORD
